{"title":"Cache","tag":"glossary/cache","post":"\n\n{{Sidebar(\"Glossary\")}}\n\nA **cache** (web cache or HTTP cache) is a component that stores HTTP responses temporarily so that it can be used for subsequent HTTP requests as long as it meets certain conditions.\n\n## See also\n\n- [Web cache](https://en.wikipedia.org/wiki/Web_cache) on Wikipedia\n","slug":"26acf2dafc764c64b0db1425f28348bb","authors":"Admin Es Solution","draft":false,"datecreated":"2025-07-05T09:58:58.310Z","dateupdated":"2025-07-05T09:58:58.310Z","layout":"PostBanner"}